devgoldyutils/__init__.py
devgoldyutils/colours.py
devgoldyutils/debugging.py
devgoldyutils/logging.py
devgoldyutils/strings.py
devgoldyutils-3.0.0.dist-info/LICENSE
devgoldyutils-3.0.0.dist-info/METADATA
devgoldyutils-3.0.0.dist-info/WHEEL
devgoldyutils-3.0.0.dist-info/top_level.txt
devgoldyutils-3.0.0.dist-info/RECORD
