Metadata-Version: 2.1
Name: devgoldyutils
Version: 3.0.0
Summary: My own utils library I use throughout all my python projects.
Author-email: Goldy <goldy@devgoldy.me>
License: GNU GENERAL PUBLIC LICENSE
Project-URL: GitHub, https://github.com/THEGOLDENPRO/devgoldyutils
Project-URL: BugTracker, https://github.com/THEGOLDENPRO/devgoldyutils/issues
Project-URL: ChangeLog, https://github.com/THEGOLDENPRO/devgoldyutils/master/CHANGELOG.md
Keywords: Goldy Utils,Dev Goldy Utils,devgoldyutils,devgoldy
Classifier: Operating System :: Microsoft :: Windows :: Windows 11
Classifier: Operating System :: Microsoft :: Windows :: Windows 10
Classifier: Operating System :: POSIX :: Linux
Classifier: License :: OSI Approved :: MIT License
Classifier: Programming Language :: Python :: 3.7
Classifier: Programming Language :: Python :: 3.8
Classifier: Programming Language :: Python :: 3.9
Classifier: Programming Language :: Python :: 3.10
Classifier: Programming Language :: Python :: 3.11
Classifier: Programming Language :: Python :: 3.12
Requires-Python: >=3.7
License-File: LICENSE
Provides-Extra: dev
Requires-Dist: ruff ; extra == 'dev'
Provides-Extra: pprint
Requires-Dist: prettyprinter ; extra == 'pprint'
